pytest_helm_templates/__init__.py
pytest_helm_templates/__version__.py
pytest_helm_templates/helm_runner.py
pytest_helm_templates/py.typed
pytest_helm_templates/types.py
pytest_helm_templates/commands/__init__.py
pytest_helm_templates/commands/show_values_command.py
pytest_helm_templates/commands/template_command.py
pytest_helm_templates-0.0.1a10.dist-info/LICENSE
pytest_helm_templates-0.0.1a10.dist-info/METADATA
pytest_helm_templates-0.0.1a10.dist-info/WHEEL
pytest_helm_templates-0.0.1a10.dist-info/top_level.txt
pytest_helm_templates-0.0.1a10.dist-info/RECORD
