Metadata-Version: 2.1
Name: pytest-helm-templates
Version: 0.0.1a10
Summary: Pytest fixtures for unit testing the output of helm templates
Author: Danny Guinther
License: MIT
Project-URL: Homepage, https://github.com/tdg5/pytest-helm-templates
Project-URL: Source, https://github.com/tdg5/pytest-helm-templates
Project-URL: Tracker, https://github.com/tdg5/pytest-helm-templates/issues
Classifier: Framework :: Pytest
Classifier: Intended Audience :: Developers
Classifier: License :: OSI Approved :: MIT License
Classifier: Operating System :: OS Independent
Classifier: Programming Language :: Python :: 3
Classifier: Programming Language :: Python :: 3.9
Classifier: Programming Language :: Python :: 3.10
Classifier: Programming Language :: Python :: 3.11
Classifier: Programming Language :: Python :: 3.12
Requires-Python: >3.9.0
License-File: LICENSE
Requires-Dist: pyyaml ~=6.0.1
Provides-Extra: all
Requires-Dist: pytest-helm-templates[dev] ; extra == 'all'
Provides-Extra: dev
Requires-Dist: black ~=24.3 ; extra == 'dev'
Requires-Dist: build ~=1.0.3 ; extra == 'dev'
Requires-Dist: coverage ~=7.4.4 ; extra == 'dev'
Requires-Dist: coverage-badge ~=1.1.0 ; extra == 'dev'
Requires-Dist: dlint ~=0.14.1 ; extra == 'dev'
Requires-Dist: flake8-comprehensions ~=3.14.0 ; extra == 'dev'
Requires-Dist: flake8-eradicate ~=1.5.0 ; extra == 'dev'
Requires-Dist: flake8-pyproject ~=1.2.3 ; extra == 'dev'
Requires-Dist: flake8-spellcheck ~=0.28.0 ; extra == 'dev'
Requires-Dist: flake8-typing-imports ~=1.15.0 ; extra == 'dev'
Requires-Dist: flake8 ~=7.0.0 ; extra == 'dev'
Requires-Dist: isort ~=5.13.2 ; extra == 'dev'
Requires-Dist: mypy ~=1.8.0 ; extra == 'dev'
Requires-Dist: pep8-naming ~=0.13.3 ; extra == 'dev'
Requires-Dist: pre-commit ~=3.6.0 ; extra == 'dev'
Requires-Dist: pytest-mock ~=3.12.0 ; extra == 'dev'
Requires-Dist: pytest-watcher ~=0.4.2 ; extra == 'dev'
Requires-Dist: pytest ~=7.4.0 ; extra == 'dev'
Requires-Dist: safety ==2.3.4 ; extra == 'dev'
Requires-Dist: twine ~=4.0.2 ; extra == 'dev'
Requires-Dist: types-PyYAML ~=6.0.12.20240311 ; extra == 'dev'
Requires-Dist: wheel >=0.42.0 ; extra == 'dev'
